[
  {
    "regionId": "usdodcentral",
    "displayName": "USDoD Central",
    "longName": "",
    "geography": "USGov",
    "geographicGroup": "United States",
    "regionGroup": "United States",
    "latitude": 41.6005,
    "longitude": -93.6091,
    "datacenterLocation": "Iowa",
    "pairedRegion": "USDoD East",
    "availabilityZoneCount": 0,
    "restricted": false,
    "availableTo": "US government entities and their partners only"
  },
  {
    "regionId": "usdodeast",
    "displayName": "USDoD East",
    "longName": "",
    "geography": "USGov",
    "geographicGroup": "United States",
    "regionGroup": "United States",
    "latitude": 36.6676,
    "longitude": -78.3875,
    "datacenterLocation": "Virginia",
    "pairedRegion": "USDoD Central",
    "availabilityZoneCount": 0,
    "restricted": false,
    "availableTo": "US government entities and their partners only"
  },
  {
    "regionId": "usgovarizona",
    "displayName": "USGov Arizona",
    "longName": "",
    "geography": "USGov",
    "geographicGroup": "United States",
    "regionGroup": "United States",
    "latitude": 33.4484,
    "longitude": -112.074,
    "datacenterLocation": "Arizona",
    "pairedRegion": "USGov Texas",
    "availabilityZoneCount": 2,
    "restricted": false,
    "availableTo": "US government entities and their partners only"
  },
  {
    "regionId": "usgovtexas",
    "displayName": "USGov Texas",
    "longName": "",
    "geography": "USGov",
    "geographicGroup": "United States",
    "regionGroup": "United States",
    "latitude": 29.4241,
    "longitude": -98.4936,
    "datacenterLocation": "Texas",
    "pairedRegion": "USGov Arizona",
    "availabilityZoneCount": 0,
    "restricted": false,
    "availableTo": "US government entities and their partners only"
  },
  {
    "regionId": "usgovvirginia",
    "displayName": "USGov Virginia",
    "longName": "",
    "geography": "USGov",
    "geographicGroup": "United States",
    "regionGroup": "United States",
    "latitude": 37.3719,
    "longitude": -79.8164,
    "datacenterLocation": "Virginia",
    "pairedRegion": "USGov Virginia",
    "availabilityZoneCount": 1,
    "restricted": false,
    "availableTo": "US government entities and their partners only"
  }
]
