<?xml version="1.0" encoding="utf-8"?>
<AzurePublicIpAddresses xmlns:xsd="http://www.w3.org/2001/XMLSchema" xmlns:xsi="http://www.w3.org/2001/XMLSchema-instance">
  <Region Name="europewest">
    <IpRange Subnet="40.112.124.0/24" />
    <IpRange Subnet="65.52.128.0/19" />
    <IpRange Subnet="94.245.97.0/24" />
    <IpRange Subnet="104.47.169.0/24" />
    <IpRange Subnet="104.214.240.0/24" />
    <IpRange Subnet="137.116.192.0/19" />
    <IpRange Subnet="157.55.8.96/27" />
    <IpRange Subnet="157.55.8.128/27" />
    <IpRange Subnet="157.55.8.160/28" />
    <IpRange Subnet="168.63.0.0/19" />
    <IpRange Subnet="168.63.96.0/19" />
    <IpRange Subnet="193.149.80.0/22" />
    <IpRange Subnet="213.199.128.0/21" />
    <IpRange Subnet="213.199.136.0/22" />
    <IpRange Subnet="213.199.180.32/28" />
    <IpRange Subnet="213.199.180.112/28" />
    <IpRange Subnet="213.199.183.0/24" />
    <IpRange Subnet="23.97.128.0/17" />
    <IpRange Subnet="23.98.46.0/24" />
    <IpRange Subnet="23.100.0.0/20" />
    <IpRange Subnet="23.101.64.0/20" />
    <IpRange Subnet="40.114.128.0/24" />
    <IpRange Subnet="40.114.136.0/21" />
    <IpRange Subnet="40.114.144.0/21" />
    <IpRange Subnet="40.114.152.0/26" />
    <IpRange Subnet="104.40.128.0/17" />
    <IpRange Subnet="104.45.0.0/18" />
    <IpRange Subnet="104.45.64.0/20" />
    <IpRange Subnet="104.46.32.0/19" />
    <IpRange Subnet="137.117.128.0/17" />
    <IpRange Subnet="168.61.56.0/21" />
    <IpRange Subnet="191.233.64.0/18" />
    <IpRange Subnet="191.237.232.0/22" />
    <IpRange Subnet="191.239.200.0/23" />
    <IpRange Subnet="191.239.202.0/24" />
    <IpRange Subnet="191.239.203.0/27" />
    <IpRange Subnet="191.239.203.64/27" />
    <IpRange Subnet="193.149.84.0/22" />
    <IpRange Subnet="40.74.0.0/20" />
    <IpRange Subnet="40.74.16.0/20" />
    <IpRange Subnet="40.74.32.0/20" />
    <IpRange Subnet="40.74.48.0/20" />
    <IpRange Subnet="40.114.129.0/24" />
    <IpRange Subnet="40.114.130.0/23" />
    <IpRange Subnet="40.114.132.0/22" />
    <IpRange Subnet="40.114.152.64/26" />
    <IpRange Subnet="40.114.152.128/25" />
    <IpRange Subnet="40.114.153.0/24" />
    <IpRange Subnet="40.114.154.0/23" />
    <IpRange Subnet="40.114.156.0/22" />
    <IpRange Subnet="40.114.160.0/19" />
    <IpRange Subnet="13.69.0.0/17" />
    <IpRange Subnet="13.73.128.0/18" />
    <IpRange Subnet="13.80.0.0/15" />
    <IpRange Subnet="40.80.0.0/18" />
    <IpRange Subnet="40.82.0.0/16" />
    <IpRange Subnet="40.112.36.128/26" />
    <IpRange Subnet="40.112.96.0/20" />
    <IpRange Subnet="40.112.112.0/21" />
    <IpRange Subnet="40.112.120.0/22" />
    <IpRange Subnet="40.112.125.0/24" />
    <IpRange Subnet="40.112.126.0/23" />
    <IpRange Subnet="40.113.96.0/19" />
    <IpRange Subnet="40.113.128.0/18" />
    <IpRange Subnet="40.114.192.0/18" />
    <IpRange Subnet="40.115.0.0/18" />
    <IpRange Subnet="40.118.0.0/17" />
    <IpRange Subnet="104.46.16.0/21" />
    <IpRange Subnet="104.47.128.0/19" />
    <IpRange Subnet="104.47.160.0/21" />
    <IpRange Subnet="104.47.168.0/24" />
    <IpRange Subnet="104.47.170.0/23" />
    <IpRange Subnet="104.47.172.0/22" />
    <IpRange Subnet="104.47.176.0/20" />
    <IpRange Subnet="104.214.192.0/19" />
    <IpRange Subnet="104.214.224.0/20" />
    <IpRange Subnet="104.214.241.0/24" />
    <IpRange Subnet="104.214.242.0/23" />
    <IpRange Subnet="104.214.244.0/22" />
    <IpRange Subnet="104.214.248.0/21" />
  </Region>
  <Region Name="useast">
    <IpRange Subnet="23.96.0.0/18" />
    <IpRange Subnet="23.96.64.0/28" />
    <IpRange Subnet="23.96.64.64/26" />
    <IpRange Subnet="23.96.64.128/27" />
    <IpRange Subnet="23.96.64.160/28" />
    <IpRange Subnet="23.96.80.0/20" />
    <IpRange Subnet="23.96.96.0/19" />
    <IpRange Subnet="23.100.16.0/20" />
    <IpRange Subnet="23.101.128.0/20" />
    <IpRange Subnet="137.116.112.0/20" />
    <IpRange Subnet="137.117.32.0/19" />
    <IpRange Subnet="137.117.64.0/18" />
    <IpRange Subnet="137.135.64.0/18" />
    <IpRange Subnet="157.56.176.0/21" />
    <IpRange Subnet="168.61.32.0/20" />
    <IpRange Subnet="168.61.48.0/21" />
    <IpRange Subnet="168.62.32.0/19" />
    <IpRange Subnet="168.62.160.0/19" />
    <IpRange Subnet="104.45.128.0/20" />
    <IpRange Subnet="104.45.144.0/20" />
    <IpRange Subnet="104.45.160.0/20" />
    <IpRange Subnet="104.45.176.0/20" />
    <IpRange Subnet="104.45.192.0/20" />
    <IpRange Subnet="23.98.45.0/24" />
    <IpRange Subnet="104.41.128.0/19" />
    <IpRange Subnet="138.91.96.0/25" />
    <IpRange Subnet="138.91.96.128/26" />
    <IpRange Subnet="138.91.96.192/28" />
    <IpRange Subnet="138.91.112.0/20" />
    <IpRange Subnet="191.234.32.0/19" />
    <IpRange Subnet="191.236.0.0/18" />
    <IpRange Subnet="191.238.0.0/22" />
    <IpRange Subnet="191.238.4.0/24" />
    <IpRange Subnet="191.238.6.0/26" />
    <IpRange Subnet="191.238.6.64/28" />
    <IpRange Subnet="191.238.7.0/24" />
    <IpRange Subnet="191.238.8.0/21" />
    <IpRange Subnet="191.238.16.0/20" />
    <IpRange Subnet="191.238.32.0/19" />
    <IpRange Subnet="40.76.0.0/20" />
    <IpRange Subnet="40.76.16.0/20" />
    <IpRange Subnet="40.76.32.0/20" />
    <IpRange Subnet="40.76.48.0/20" />
    <IpRange Subnet="13.68.163.16/28" />
    <IpRange Subnet="13.68.163.32/27" />
    <IpRange Subnet="13.68.163.64/26" />
    <IpRange Subnet="13.68.163.128/25" />
    <IpRange Subnet="13.68.164.0/22" />
    <IpRange Subnet="13.68.224.0/19" />
    <IpRange Subnet="40.76.64.0/18" />
    <IpRange Subnet="40.76.128.0/17" />
    <IpRange Subnet="40.114.0.0/17" />
    <IpRange Subnet="40.117.128.0/17" />
    <IpRange Subnet="40.121.0.0/16" />
    <IpRange Subnet="104.211.0.0/18" />
    <IpRange Subnet="191.237.0.0/19" />
    <IpRange Subnet="191.237.32.0/22" />
    <IpRange Subnet="191.237.36.0/23" />
    <IpRange Subnet="191.237.38.0/27" />
    <IpRange Subnet="191.237.39.0/24" />
    <IpRange Subnet="191.237.40.0/21" />
    <IpRange Subnet="191.237.48.0/20" />
    <IpRange Subnet="191.237.64.0/18" />
    <IpRange Subnet="13.72.88.0/28" />
    <IpRange Subnet="13.72.88.32/27" />
    <IpRange Subnet="13.72.88.64/26" />
    <IpRange Subnet="13.72.88.128/25" />
    <IpRange Subnet="13.72.90.0/23" />
    <IpRange Subnet="13.72.92.0/22" />
    <IpRange Subnet="13.68.161.16/28" />
    <IpRange Subnet="13.68.161.32/27" />
    <IpRange Subnet="13.68.161.64/26" />
    <IpRange Subnet="13.68.161.128/25" />
    <IpRange Subnet="13.72.104.0/21" />
    <IpRange Subnet="13.72.112.0/20" />
    <IpRange Subnet="13.68.128.0/19" />
    <IpRange Subnet="13.68.160.0/24" />
    <IpRange Subnet="13.68.161.0/28" />
    <IpRange Subnet="13.68.162.0/24" />
    <IpRange Subnet="13.68.163.0/28" />
    <IpRange Subnet="13.68.168.0/21" />
    <IpRange Subnet="13.68.176.0/20" />
    <IpRange Subnet="13.68.192.0/19" />
    <IpRange Subnet="13.72.64.0/20" />
    <IpRange Subnet="13.72.80.0/21" />
    <IpRange Subnet="13.72.88.16/28" />
    <IpRange Subnet="13.72.89.0/24" />
    <IpRange Subnet="13.72.96.0/21" />
    <IpRange Subnet="13.82.0.0/16" />
    <IpRange Subnet="40.80.144.0/21" />
    <IpRange Subnet="40.85.160.0/19" />
    <IpRange Subnet="40.87.0.0/17" />
    <IpRange Subnet="40.112.48.0/20" />
    <IpRange Subnet="40.117.32.0/19" />
    <IpRange Subnet="40.117.64.0/18" />
  </Region>
  <Region Name="useast2">
    <IpRange Subnet="23.100.64.0/21" />
    <IpRange Subnet="23.101.144.0/20" />
    <IpRange Subnet="23.101.32.0/21" />
    <IpRange Subnet="137.116.0.0/18" />
    <IpRange Subnet="137.116.64.0/19" />
    <IpRange Subnet="137.116.96.0/22" />
    <IpRange Subnet="191.239.224.0/25" />
    <IpRange Subnet="193.149.64.0/21" />
    <IpRange Subnet="104.46.192.0/20" />
    <IpRange Subnet="23.102.204.0/23" />
    <IpRange Subnet="23.102.206.0/25" />
    <IpRange Subnet="23.102.206.128/28" />
    <IpRange Subnet="23.102.207.0/24" />
    <IpRange Subnet="40.75.0.0/17" />
    <IpRange Subnet="40.84.0.0/21" />
    <IpRange Subnet="40.84.8.0/27" />
    <IpRange Subnet="40.84.8.32/28" />
    <IpRange Subnet="40.84.9.0/24" />
    <IpRange Subnet="40.84.16.0/20" />
    <IpRange Subnet="104.46.0.0/21" />
    <IpRange Subnet="104.46.96.0/19" />
    <IpRange Subnet="104.47.200.0/24" />
    <IpRange Subnet="104.47.201.0/28" />
    <IpRange Subnet="104.209.128.0/18" />
    <IpRange Subnet="104.209.192.0/19" />
    <IpRange Subnet="104.209.224.0/24" />
    <IpRange Subnet="104.209.225.0/28" />
    <IpRange Subnet="104.209.232.0/21" />
    <IpRange Subnet="104.209.240.0/20" />
    <IpRange Subnet="104.210.0.0/20" />
    <IpRange Subnet="191.236.192.0/18" />
    <IpRange Subnet="191.237.128.0/19" />
    <IpRange Subnet="191.237.160.0/22" />
    <IpRange Subnet="191.237.164.0/23" />
    <IpRange Subnet="191.237.168.0/21" />
    <IpRange Subnet="191.237.176.0/20" />
    <IpRange Subnet="23.102.206.144/28" />
    <IpRange Subnet="23.102.206.160/27" />
    <IpRange Subnet="23.102.206.192/26" />
    <IpRange Subnet="104.47.201.16/28" />
    <IpRange Subnet="104.47.201.32/27" />
    <IpRange Subnet="104.47.201.64/26" />
    <IpRange Subnet="104.47.201.128/25" />
    <IpRange Subnet="104.47.202.0/23" />
    <IpRange Subnet="104.47.204.0/22" />
    <IpRange Subnet="104.209.225.16/28" />
    <IpRange Subnet="104.209.225.32/27" />
    <IpRange Subnet="104.209.225.64/26" />
    <IpRange Subnet="104.209.225.128/25" />
    <IpRange Subnet="104.209.226.0/23" />
    <IpRange Subnet="104.209.228.0/22" />
    <IpRange Subnet="40.84.8.48/28" />
    <IpRange Subnet="40.84.8.64/26" />
    <IpRange Subnet="40.84.8.128/25" />
    <IpRange Subnet="40.84.10.0/23" />
    <IpRange Subnet="40.84.12.0/22" />
    <IpRange Subnet="40.84.32.0/19" />
    <IpRange Subnet="40.84.64.0/18" />
    <IpRange Subnet="13.68.0.0/17" />
    <IpRange Subnet="13.77.64.0/18" />
    <IpRange Subnet="40.79.0.0/21" />
    <IpRange Subnet="40.79.8.32/28" />
    <IpRange Subnet="40.79.8.64/27" />
    <IpRange Subnet="40.79.8.96/28" />
    <IpRange Subnet="40.79.9.0/24" />
    <IpRange Subnet="40.79.16.0/20" />
    <IpRange Subnet="40.79.32.0/20" />
    <IpRange Subnet="40.79.48.0/27" />
    <IpRange Subnet="40.79.92.0/24" />
    <IpRange Subnet="40.79.93.0/28" />
    <IpRange Subnet="40.81.0.0/17" />
    <IpRange Subnet="40.123.16.0/27" />
    <IpRange Subnet="40.123.16.32/28" />
    <IpRange Subnet="40.123.17.0/24" />
    <IpRange Subnet="40.123.24.0/21" />
    <IpRange Subnet="40.123.32.0/20" />
    <IpRange Subnet="40.123.48.0/21" />
    <IpRange Subnet="40.123.120.0/21" />
    <IpRange Subnet="104.208.128.0/27" />
    <IpRange Subnet="104.208.128.32/28" />
    <IpRange Subnet="104.208.129.0/24" />
    <IpRange Subnet="104.208.136.0/21" />
    <IpRange Subnet="104.208.144.0/20" />
    <IpRange Subnet="104.208.160.0/21" />
    <IpRange Subnet="104.208.192.0/20" />
    <IpRange Subnet="104.208.208.0/24" />
    <IpRange Subnet="104.208.209.0/28" />
    <IpRange Subnet="104.208.216.0/21" />
    <IpRange Subnet="104.208.224.0/20" />
    <IpRange Subnet="104.208.240.0/21" />
    <IpRange Subnet="104.208.248.0/27" />
  </Region>
  <Region Name="uswest">
    <IpRange Subnet="23.100.32.0/20" />
    <IpRange Subnet="23.101.192.0/20" />
    <IpRange Subnet="137.116.184.0/21" />
    <IpRange Subnet="137.117.0.0/19" />
    <IpRange Subnet="137.135.0.0/18" />
    <IpRange Subnet="138.91.64.0/19" />
    <IpRange Subnet="157.56.160.0/21" />
    <IpRange Subnet="168.61.0.0/19" />
    <IpRange Subnet="168.61.64.0/20" />
    <IpRange Subnet="168.62.0.0/19" />
    <IpRange Subnet="168.62.192.0/19" />
    <IpRange Subnet="168.63.88.0/24" />
    <IpRange Subnet="104.45.208.0/20" />
    <IpRange Subnet="104.45.224.0/20" />
    <IpRange Subnet="104.45.240.0/20" />
    <IpRange Subnet="23.99.64.0/19" />
    <IpRange Subnet="138.91.128.0/24" />
    <IpRange Subnet="138.91.129.0/26" />
    <IpRange Subnet="138.91.129.64/28" />
    <IpRange Subnet="138.91.136.0/21" />
    <IpRange Subnet="138.91.144.0/20" />
    <IpRange Subnet="138.91.160.0/19" />
    <IpRange Subnet="138.91.192.0/21" />
    <IpRange Subnet="138.91.224.0/19" />
    <IpRange Subnet="191.238.70.0/23" />
    <IpRange Subnet="23.99.0.0/19" />
    <IpRange Subnet="23.99.32.0/25" />
    <IpRange Subnet="23.99.32.128/28" />
    <IpRange Subnet="23.99.33.0/28" />
    <IpRange Subnet="23.99.34.0/23" />
    <IpRange Subnet="23.99.36.0/24" />
    <IpRange Subnet="23.99.37.0/26" />
    <IpRange Subnet="23.99.37.80/28" />
    <IpRange Subnet="23.99.37.96/27" />
    <IpRange Subnet="23.99.37.128/27" />
    <IpRange Subnet="23.99.37.176/28" />
    <IpRange Subnet="23.99.37.192/26" />
    <IpRange Subnet="23.99.38.0/24" />
    <IpRange Subnet="23.99.40.0/23" />
    <IpRange Subnet="23.99.42.0/24" />
    <IpRange Subnet="23.99.44.0/23" />
    <IpRange Subnet="23.99.46.0/24" />
    <IpRange Subnet="23.99.47.0/26" />
    <IpRange Subnet="23.99.47.64/28" />
    <IpRange Subnet="23.99.48.0/20" />
    <IpRange Subnet="40.75.128.0/17" />
    <IpRange Subnet="40.83.152.0/24" />
    <IpRange Subnet="40.83.153.0/28" />
    <IpRange Subnet="40.83.160.0/19" />
    <IpRange Subnet="40.83.227.0/27" />
    <IpRange Subnet="40.112.224.0/26" />
    <IpRange Subnet="65.52.112.0/20" />
    <IpRange Subnet="104.40.0.0/18" />
    <IpRange Subnet="104.40.64.0/19" />
    <IpRange Subnet="104.42.0.0/18" />
    <IpRange Subnet="104.42.64.0/20" />
    <IpRange Subnet="104.42.96.0/19" />
    <IpRange Subnet="104.209.16.0/23" />
    <IpRange Subnet="104.209.32.0/19" />
    <IpRange Subnet="104.210.32.0/19" />
    <IpRange Subnet="168.63.89.0/25" />
    <IpRange Subnet="168.63.89.128/26" />
    <IpRange Subnet="191.236.64.0/18" />
    <IpRange Subnet="191.239.0.0/18" />
    <IpRange Subnet="13.83.0.0/16" />
    <IpRange Subnet="40.78.0.0/17" />
    <IpRange Subnet="40.81.128.0/17" />
    <IpRange Subnet="40.112.128.0/18" />
    <IpRange Subnet="40.112.192.0/19" />
    <IpRange Subnet="40.112.224.64/26" />
    <IpRange Subnet="40.112.225.0/24" />
    <IpRange Subnet="40.112.232.0/21" />
    <IpRange Subnet="40.112.240.0/20" />
    <IpRange Subnet="40.118.128.0/17" />
    <IpRange Subnet="40.80.152.0/21" />
    <IpRange Subnet="40.83.128.0/20" />
    <IpRange Subnet="40.83.144.0/21" />
    <IpRange Subnet="40.83.153.16/28" />
    <IpRange Subnet="40.83.153.32/27" />
    <IpRange Subnet="40.83.153.64/26" />
    <IpRange Subnet="40.83.153.128/25" />
    <IpRange Subnet="40.83.154.0/23" />
    <IpRange Subnet="40.83.156.0/22" />
    <IpRange Subnet="40.85.144.0/20" />
    <IpRange Subnet="40.86.160.0/19" />
    <IpRange Subnet="40.112.224.128/25" />
    <IpRange Subnet="40.112.226.0/23" />
    <IpRange Subnet="40.112.228.0/22" />
    <IpRange Subnet="13.64.0.0/16" />
    <IpRange Subnet="13.73.32.0/19" />
    <IpRange Subnet="104.42.128.0/17" />
    <IpRange Subnet="40.83.192.0/19" />
    <IpRange Subnet="40.83.224.0/23" />
    <IpRange Subnet="40.83.226.0/24" />
    <IpRange Subnet="40.83.227.32/27" />
    <IpRange Subnet="40.83.227.64/26" />
    <IpRange Subnet="40.83.227.128/25" />
    <IpRange Subnet="40.83.228.0/22" />
    <IpRange Subnet="40.83.232.0/21" />
    <IpRange Subnet="40.83.240.0/20" />
  </Region>
  <Region Name="usnorth">
    <IpRange Subnet="23.98.54.0/24" />
    <IpRange Subnet="23.100.72.0/21" />
    <IpRange Subnet="23.100.224.0/20" />
    <IpRange Subnet="40.116.0.0/28" />
    <IpRange Subnet="40.116.0.32/27" />
    <IpRange Subnet="40.116.1.0/24" />
    <IpRange Subnet="40.116.24.0/21" />
    <IpRange Subnet="40.116.32.0/21" />
    <IpRange Subnet="40.116.40.0/28" />
    <IpRange Subnet="40.116.40.32/27" />
    <IpRange Subnet="65.52.0.0/19" />
    <IpRange Subnet="65.52.48.0/20" />
    <IpRange Subnet="65.52.106.16/28" />
    <IpRange Subnet="65.52.106.128/27" />
    <IpRange Subnet="65.52.106.240/28" />
    <IpRange Subnet="65.52.192.0/19" />
    <IpRange Subnet="65.52.232.0/21" />
    <IpRange Subnet="65.52.240.0/21" />
    <IpRange Subnet="157.55.24.0/21" />
    <IpRange Subnet="157.55.60.224/27" />
    <IpRange Subnet="157.55.73.32/28" />
    <IpRange Subnet="157.55.136.0/21" />
    <IpRange Subnet="157.55.160.0/20" />
    <IpRange Subnet="157.55.208.0/21" />
    <IpRange Subnet="157.55.252.0/22" />
    <IpRange Subnet="157.56.8.0/21" />
    <IpRange Subnet="157.56.24.160/27" />
    <IpRange Subnet="157.56.24.192/28" />
    <IpRange Subnet="157.56.28.0/22" />
    <IpRange Subnet="168.62.96.0/19" />
    <IpRange Subnet="168.62.224.0/20" />
    <IpRange Subnet="168.62.240.0/21" />
    <IpRange Subnet="168.62.248.0/22" />
    <IpRange Subnet="191.233.144.0/24" />
    <IpRange Subnet="207.46.192.0/24" />
    <IpRange Subnet="207.46.193.0/25" />
    <IpRange Subnet="207.46.193.144/28" />
    <IpRange Subnet="207.46.193.160/27" />
    <IpRange Subnet="207.46.193.192/26" />
    <IpRange Subnet="207.46.194.0/23" />
    <IpRange Subnet="207.46.196.0/23" />
    <IpRange Subnet="207.46.198.0/24" />
    <IpRange Subnet="207.46.199.0/26" />
    <IpRange Subnet="207.46.199.64/27" />
    <IpRange Subnet="207.46.199.128/25" />
    <IpRange Subnet="207.46.200.0/26" />
    <IpRange Subnet="207.46.200.64/28" />
    <IpRange Subnet="207.46.200.96/27" />
    <IpRange Subnet="207.46.200.128/25" />
    <IpRange Subnet="207.46.201.0/24" />
    <IpRange Subnet="207.46.202.0/24" />
    <IpRange Subnet="207.46.203.0/26" />
    <IpRange Subnet="207.46.203.128/26" />
    <IpRange Subnet="207.46.203.192/27" />
    <IpRange Subnet="207.46.204.0/22" />
    <IpRange Subnet="209.240.220.0/23" />
    <IpRange Subnet="23.96.176.0/20" />
    <IpRange Subnet="23.96.192.0/18" />
    <IpRange Subnet="23.98.48.0/27" />
    <IpRange Subnet="23.98.48.80/28" />
    <IpRange Subnet="23.98.48.96/27" />
    <IpRange Subnet="23.98.48.128/27" />
    <IpRange Subnet="23.98.48.160/28" />
    <IpRange Subnet="23.98.48.192/26" />
    <IpRange Subnet="23.98.49.0/24" />
    <IpRange Subnet="23.98.50.0/23" />
    <IpRange Subnet="23.98.52.0/23" />
    <IpRange Subnet="23.98.55.0/25" />
    <IpRange Subnet="23.98.55.128/27" />
    <IpRange Subnet="23.101.160.0/20" />
    <IpRange Subnet="191.233.168.0/21" />
    <IpRange Subnet="191.233.176.0/21" />
    <IpRange Subnet="191.236.128.0/18" />
    <IpRange Subnet="23.98.55.160/27" />
    <IpRange Subnet="23.98.55.192/26" />
    <IpRange Subnet="13.71.192.0/18" />
  </Region>
  <Region Name="europenorth">
    <IpRange Subnet="40.113.24.0/24" />
    <IpRange Subnet="65.52.64.0/20" />
    <IpRange Subnet="65.52.224.0/21" />
    <IpRange Subnet="94.245.88.0/21" />
    <IpRange Subnet="94.245.104.0/21" />
    <IpRange Subnet="94.245.112.0/23" />
    <IpRange Subnet="94.245.114.64/26" />
    <IpRange Subnet="94.245.114.128/25" />
    <IpRange Subnet="94.245.115.0/24" />
    <IpRange Subnet="94.245.116.0/24" />
    <IpRange Subnet="94.245.117.0/26" />
    <IpRange Subnet="94.245.117.96/27" />
    <IpRange Subnet="94.245.117.128/25" />
    <IpRange Subnet="94.245.118.0/27" />
    <IpRange Subnet="94.245.120.0/25" />
    <IpRange Subnet="94.245.120.128/28" />
    <IpRange Subnet="94.245.120.160/27" />
    <IpRange Subnet="94.245.120.192/26" />
    <IpRange Subnet="94.245.121.0/24" />
    <IpRange Subnet="94.245.122.0/24" />
    <IpRange Subnet="94.245.123.0/25" />
    <IpRange Subnet="94.245.123.128/27" />
    <IpRange Subnet="94.245.123.176/28" />
    <IpRange Subnet="94.245.123.192/26" />
    <IpRange Subnet="94.245.124.0/22" />
    <IpRange Subnet="104.41.233.0/24" />
    <IpRange Subnet="137.116.224.0/19" />
    <IpRange Subnet="168.61.80.0/20" />
    <IpRange Subnet="168.61.96.0/19" />
    <IpRange Subnet="168.63.32.0/19" />
    <IpRange Subnet="168.63.64.0/20" />
    <IpRange Subnet="168.63.80.0/21" />
    <IpRange Subnet="168.63.92.0/22" />
    <IpRange Subnet="193.149.88.0/21" />
    <IpRange Subnet="23.100.48.0/20" />
    <IpRange Subnet="23.101.48.0/20" />
    <IpRange Subnet="23.102.0.0/18" />
    <IpRange Subnet="104.45.80.0/20" />
    <IpRange Subnet="104.45.96.0/19" />
    <IpRange Subnet="137.135.128.0/20" />
    <IpRange Subnet="137.135.160.0/19" />
    <IpRange Subnet="137.135.192.0/25" />
    <IpRange Subnet="137.135.192.128/28" />
    <IpRange Subnet="137.135.192.160/27" />
    <IpRange Subnet="137.135.192.192/26" />
    <IpRange Subnet="137.135.193.0/24" />
    <IpRange Subnet="137.135.194.0/23" />
    <IpRange Subnet="137.135.196.0/22" />
    <IpRange Subnet="137.135.200.0/21" />
    <IpRange Subnet="137.135.208.0/20" />
    <IpRange Subnet="137.135.224.0/19" />
    <IpRange Subnet="138.91.48.0/20" />
    <IpRange Subnet="191.235.128.0/18" />
    <IpRange Subnet="191.235.192.0/24" />
    <IpRange Subnet="191.235.193.0/26" />
    <IpRange Subnet="191.235.193.64/27" />
    <IpRange Subnet="191.235.193.96/28" />
    <IpRange Subnet="191.235.193.128/25" />
    <IpRange Subnet="191.235.194.0/23" />
    <IpRange Subnet="191.235.208.0/20" />
    <IpRange Subnet="191.235.255.0/26" />
    <IpRange Subnet="191.235.255.64/27" />
    <IpRange Subnet="191.235.255.128/25" />
    <IpRange Subnet="191.237.192.0/23" />
    <IpRange Subnet="191.237.194.0/24" />
    <IpRange Subnet="191.237.196.0/28" />
    <IpRange Subnet="191.237.208.0/20" />
    <IpRange Subnet="191.238.96.0/19" />
    <IpRange Subnet="191.239.208.0/20" />
    <IpRange Subnet="40.127.128.0/19" />
    <IpRange Subnet="40.127.160.0/19" />
    <IpRange Subnet="13.69.128.0/17" />
    <IpRange Subnet="13.70.192.0/18" />
    <IpRange Subnet="13.74.0.0/16" />
    <IpRange Subnet="13.79.0.0/16" />
    <IpRange Subnet="40.74.144.0/20" />
    <IpRange Subnet="40.79.128.0/17" />
    <IpRange Subnet="40.85.0.0/17" />
    <IpRange Subnet="40.85.128.0/20" />
    <IpRange Subnet="40.87.128.0/19" />
    <IpRange Subnet="40.112.36.0/26" />
    <IpRange Subnet="40.112.64.0/19" />
    <IpRange Subnet="40.113.0.0/20" />
    <IpRange Subnet="40.113.16.0/21" />
    <IpRange Subnet="40.113.25.0/24" />
    <IpRange Subnet="40.113.26.0/23" />
    <IpRange Subnet="40.113.28.0/22" />
    <IpRange Subnet="40.113.32.0/19" />
    <IpRange Subnet="40.113.64.0/19" />
    <IpRange Subnet="40.115.96.0/19" />
    <IpRange Subnet="40.127.96.0/20" />
    <IpRange Subnet="40.127.192.0/18" />
    <IpRange Subnet="104.41.192.0/19" />
    <IpRange Subnet="104.41.224.0/21" />
    <IpRange Subnet="104.41.232.0/24" />
    <IpRange Subnet="104.41.234.0/23" />
    <IpRange Subnet="104.41.236.0/22" />
    <IpRange Subnet="104.41.240.0/20" />
    <IpRange Subnet="104.46.8.0/21" />
    <IpRange Subnet="104.46.64.0/19" />
  </Region>
  <Region Name="uscentral">
    <IpRange Subnet="23.100.80.0/21" />
    <IpRange Subnet="23.101.112.0/20" />
    <IpRange Subnet="168.61.128.0/17" />
    <IpRange Subnet="193.149.72.0/21" />
    <IpRange Subnet="23.100.240.0/20" />
    <IpRange Subnet="23.99.128.0/19" />
    <IpRange Subnet="23.99.160.0/22" />
    <IpRange Subnet="23.99.164.0/23" />
    <IpRange Subnet="23.99.166.0/24" />
    <IpRange Subnet="23.99.167.0/27" />
    <IpRange Subnet="23.99.168.0/23" />
    <IpRange Subnet="23.99.176.0/20" />
    <IpRange Subnet="23.99.192.0/18" />
    <IpRange Subnet="40.78.128.0/19" />
    <IpRange Subnet="40.113.192.0/20" />
    <IpRange Subnet="40.113.208.0/24" />
    <IpRange Subnet="40.113.209.0/28" />
    <IpRange Subnet="40.113.216.0/21" />
    <IpRange Subnet="40.113.224.0/20" />
    <IpRange Subnet="40.113.240.0/21" />
    <IpRange Subnet="40.113.248.0/24" />
    <IpRange Subnet="40.113.249.0/28" />
    <IpRange Subnet="104.43.128.0/17" />
    <IpRange Subnet="23.99.167.32/27" />
    <IpRange Subnet="23.99.167.64/26" />
    <IpRange Subnet="23.99.167.128/25" />
    <IpRange Subnet="23.99.170.0/23" />
    <IpRange Subnet="23.99.172.0/22" />
    <IpRange Subnet="40.78.160.0/19" />
    <IpRange Subnet="40.113.209.16/28" />
    <IpRange Subnet="40.113.209.32/27" />
    <IpRange Subnet="40.113.209.64/26" />
    <IpRange Subnet="40.113.209.128/25" />
    <IpRange Subnet="40.113.210.0/23" />
    <IpRange Subnet="40.113.212.0/22" />
    <IpRange Subnet="40.113.249.16/28" />
    <IpRange Subnet="40.113.249.32/27" />
    <IpRange Subnet="40.113.249.64/26" />
    <IpRange Subnet="40.113.249.128/25" />
    <IpRange Subnet="40.113.250.0/23" />
    <IpRange Subnet="40.113.252.0/22" />
    <IpRange Subnet="13.67.128.0/17" />
    <IpRange Subnet="13.86.0.0/17" />
    <IpRange Subnet="40.77.0.0/17" />
    <IpRange Subnet="40.83.0.0/18" />
    <IpRange Subnet="40.86.0.0/17" />
    <IpRange Subnet="40.122.0.0/16" />
    <IpRange Subnet="104.208.0.0/18" />
  </Region>
  <Region Name="asiaeast">
    <IpRange Subnet="23.98.32.0/21" />
    <IpRange Subnet="23.98.40.0/22" />
    <IpRange Subnet="23.100.88.0/21" />
    <IpRange Subnet="23.101.0.0/20" />
    <IpRange Subnet="65.52.160.0/19" />
    <IpRange Subnet="104.46.24.0/24" />
    <IpRange Subnet="104.46.26.0/24" />
    <IpRange Subnet="104.46.160.0/19" />
    <IpRange Subnet="111.221.64.0/22" />
    <IpRange Subnet="111.221.69.0/25" />
    <IpRange Subnet="134.170.192.0/21" />
    <IpRange Subnet="137.116.160.0/20" />
    <IpRange Subnet="168.63.128.0/19" />
    <IpRange Subnet="168.63.192.0/19" />
    <IpRange Subnet="207.46.87.0/24" />
    <IpRange Subnet="207.46.89.16/28" />
    <IpRange Subnet="207.46.95.48/28" />
    <IpRange Subnet="207.46.128.0/19" />
    <IpRange Subnet="13.70.0.0/18" />
    <IpRange Subnet="13.72.192.0/19" />
    <IpRange Subnet="13.75.0.0/17" />
    <IpRange Subnet="23.97.64.0/20" />
    <IpRange Subnet="23.97.80.0/28" />
    <IpRange Subnet="23.98.44.0/24" />
    <IpRange Subnet="23.99.96.0/19" />
    <IpRange Subnet="23.102.224.0/19" />
    <IpRange Subnet="40.83.64.0/18" />
    <IpRange Subnet="104.46.25.0/24" />
    <IpRange Subnet="104.46.27.0/24" />
    <IpRange Subnet="104.208.80.0/20" />
    <IpRange Subnet="104.208.96.0/19" />
    <IpRange Subnet="191.234.2.16/28" />
    <IpRange Subnet="191.234.2.32/27" />
    <IpRange Subnet="191.234.2.64/26" />
    <IpRange Subnet="191.234.2.128/26" />
    <IpRange Subnet="191.234.3.0/24" />
    <IpRange Subnet="191.234.16.0/20" />
    <IpRange Subnet="191.237.238.0/28" />
    <IpRange Subnet="191.237.238.32/27" />
    <IpRange Subnet="191.237.238.64/27" />
    <IpRange Subnet="191.237.238.112/28" />
  </Region>
  <Region Name="asiasoutheast">
    <IpRange Subnet="23.97.48.0/20" />
    <IpRange Subnet="23.100.112.0/21" />
    <IpRange Subnet="23.101.16.0/20" />
    <IpRange Subnet="104.43.41.0/24" />
    <IpRange Subnet="104.46.128.0/19" />
    <IpRange Subnet="104.215.201.0/24" />
    <IpRange Subnet="111.221.80.0/20" />
    <IpRange Subnet="111.221.96.0/20" />
    <IpRange Subnet="137.116.128.0/19" />
    <IpRange Subnet="138.91.32.0/20" />
    <IpRange Subnet="168.63.160.0/25" />
    <IpRange Subnet="168.63.160.128/27" />
    <IpRange Subnet="168.63.160.192/26" />
    <IpRange Subnet="168.63.161.0/24" />
    <IpRange Subnet="168.63.162.0/25" />
    <IpRange Subnet="168.63.162.128/27" />
    <IpRange Subnet="168.63.162.176/28" />
    <IpRange Subnet="168.63.162.192/26" />
    <IpRange Subnet="168.63.163.0/24" />
    <IpRange Subnet="168.63.164.0/22" />
    <IpRange Subnet="168.63.168.0/21" />
    <IpRange Subnet="168.63.176.0/20" />
    <IpRange Subnet="168.63.224.0/19" />
    <IpRange Subnet="207.46.48.0/21" />
    <IpRange Subnet="207.46.56.0/24" />
    <IpRange Subnet="207.46.58.0/24" />
    <IpRange Subnet="207.46.59.0/26" />
    <IpRange Subnet="207.46.59.128/25" />
    <IpRange Subnet="207.46.60.0/23" />
    <IpRange Subnet="207.46.62.0/24" />
    <IpRange Subnet="207.46.63.0/26" />
    <IpRange Subnet="207.46.63.80/28" />
    <IpRange Subnet="207.46.63.96/27" />
    <IpRange Subnet="207.46.63.128/25" />
    <IpRange Subnet="23.98.64.0/20" />
    <IpRange Subnet="168.63.90.0/27" />
    <IpRange Subnet="168.63.90.32/28" />
    <IpRange Subnet="168.63.90.64/27" />
    <IpRange Subnet="191.238.64.0/24" />
    <IpRange Subnet="207.46.224.0/20" />
    <IpRange Subnet="13.67.0.0/17" />
    <IpRange Subnet="13.76.0.0/16" />
    <IpRange Subnet="104.43.0.0/28" />
    <IpRange Subnet="104.43.1.0/24" />
    <IpRange Subnet="104.43.8.0/21" />
    <IpRange Subnet="104.43.16.0/20" />
    <IpRange Subnet="104.43.32.0/21" />
    <IpRange Subnet="104.43.64.0/20" />
    <IpRange Subnet="104.43.80.0/27" />
    <IpRange Subnet="104.43.120.0/28" />
    <IpRange Subnet="104.43.121.0/24" />
    <IpRange Subnet="104.215.128.0/19" />
    <IpRange Subnet="104.215.160.0/28" />
    <IpRange Subnet="104.215.161.0/24" />
    <IpRange Subnet="104.215.168.0/21" />
    <IpRange Subnet="104.215.176.0/20" />
    <IpRange Subnet="104.215.192.0/21" />
    <IpRange Subnet="104.215.224.0/20" />
    <IpRange Subnet="104.215.240.0/28" />
    <IpRange Subnet="104.215.240.32/27" />
    <IpRange Subnet="104.215.240.160/28" />
    <IpRange Subnet="104.215.240.192/27" />
  </Region>
  <Region Name="ussouth">
    <IpRange Subnet="23.98.174.0/24" />
    <IpRange Subnet="23.98.208.0/23" />
    <IpRange Subnet="65.52.32.0/21" />
    <IpRange Subnet="65.54.48.0/22" />
    <IpRange Subnet="65.54.52.0/26" />
    <IpRange Subnet="65.54.52.64/27" />
    <IpRange Subnet="65.54.52.128/25" />
    <IpRange Subnet="65.54.53.0/24" />
    <IpRange Subnet="65.55.80.0/21" />
    <IpRange Subnet="65.55.88.0/22" />
    <IpRange Subnet="65.55.92.0/23" />
    <IpRange Subnet="65.55.94.0/24" />
    <IpRange Subnet="65.55.95.0/26" />
    <IpRange Subnet="65.55.95.64/27" />
    <IpRange Subnet="65.55.95.128/25" />
    <IpRange Subnet="70.37.48.0/20" />
    <IpRange Subnet="70.37.64.0/19" />
    <IpRange Subnet="70.37.96.0/20" />
    <IpRange Subnet="70.37.112.0/22" />
    <IpRange Subnet="70.37.116.0/23" />
    <IpRange Subnet="70.37.118.0/24" />
    <IpRange Subnet="70.37.119.128/26" />
    <IpRange Subnet="70.37.119.224/27" />
    <IpRange Subnet="70.37.120.0/22" />
    <IpRange Subnet="70.37.124.0/23" />
    <IpRange Subnet="70.37.126.0/26" />
    <IpRange Subnet="70.37.126.64/27" />
    <IpRange Subnet="70.37.126.128/27" />
    <IpRange Subnet="70.37.126.192/26" />
    <IpRange Subnet="70.37.127.0/26" />
    <IpRange Subnet="70.37.127.240/28" />
    <IpRange Subnet="70.37.160.0/21" />
    <IpRange Subnet="104.47.208.0/23" />
    <IpRange Subnet="157.55.80.0/21" />
    <IpRange Subnet="157.55.103.32/27" />
    <IpRange Subnet="157.55.153.224/28" />
    <IpRange Subnet="157.55.176.0/20" />
    <IpRange Subnet="157.55.192.0/21" />
    <IpRange Subnet="157.55.200.0/22" />
    <IpRange Subnet="168.62.128.0/19" />
    <IpRange Subnet="13.65.0.0/16" />
    <IpRange Subnet="13.66.32.0/19" />
    <IpRange Subnet="13.66.64.0/18" />
    <IpRange Subnet="23.98.128.0/19" />
    <IpRange Subnet="23.98.160.0/25" />
    <IpRange Subnet="23.98.160.128/27" />
    <IpRange Subnet="23.98.160.160/28" />
    <IpRange Subnet="23.98.160.208/28" />
    <IpRange Subnet="23.98.160.224/27" />
    <IpRange Subnet="23.98.161.0/24" />
    <IpRange Subnet="23.98.162.0/28" />
    <IpRange Subnet="23.98.162.32/28" />
    <IpRange Subnet="23.98.162.64/26" />
    <IpRange Subnet="23.98.162.128/27" />
    <IpRange Subnet="23.98.162.176/28" />
    <IpRange Subnet="23.98.162.192/26" />
    <IpRange Subnet="23.98.164.0/23" />
    <IpRange Subnet="23.98.167.0/24" />
    <IpRange Subnet="23.98.169.0/24" />
    <IpRange Subnet="23.98.170.0/28" />
    <IpRange Subnet="23.98.170.32/27" />
    <IpRange Subnet="23.98.170.64/26" />
    <IpRange Subnet="23.98.170.128/25" />
    <IpRange Subnet="23.98.171.0/24" />
    <IpRange Subnet="23.98.173.0/24" />
    <IpRange Subnet="23.98.175.0/24" />
    <IpRange Subnet="23.98.176.0/20" />
    <IpRange Subnet="23.98.192.0/25" />
    <IpRange Subnet="23.98.210.0/23" />
    <IpRange Subnet="23.98.212.0/22" />
    <IpRange Subnet="23.98.216.0/21" />
    <IpRange Subnet="23.98.255.0/27" />
    <IpRange Subnet="23.98.255.32/28" />
    <IpRange Subnet="23.98.255.64/26" />
    <IpRange Subnet="23.100.120.0/21" />
    <IpRange Subnet="23.100.192.0/19" />
    <IpRange Subnet="23.101.176.0/20" />
    <IpRange Subnet="23.102.128.0/18" />
    <IpRange Subnet="40.74.160.0/20" />
    <IpRange Subnet="40.74.192.0/18" />
    <IpRange Subnet="104.44.128.0/19" />
    <IpRange Subnet="104.210.128.0/19" />
    <IpRange Subnet="104.210.184.0/21" />
    <IpRange Subnet="104.210.192.0/19" />
    <IpRange Subnet="104.214.0.0/17" />
    <IpRange Subnet="191.238.136.0/21" />
    <IpRange Subnet="191.238.144.0/20" />
    <IpRange Subnet="191.238.160.0/19" />
    <IpRange Subnet="191.238.224.0/19" />
    <IpRange Subnet="13.66.0.0/19" />
    <IpRange Subnet="13.84.0.0/15" />
    <IpRange Subnet="40.74.176.0/20" />
    <IpRange Subnet="40.80.160.0/19" />
    <IpRange Subnet="40.80.192.0/18" />
    <IpRange Subnet="40.84.128.0/18" />
    <IpRange Subnet="40.84.192.0/19" />
    <IpRange Subnet="40.84.224.0/20" />
    <IpRange Subnet="40.84.241.16/28" />
    <IpRange Subnet="40.84.241.32/27" />
    <IpRange Subnet="40.84.241.64/26" />
    <IpRange Subnet="40.84.241.128/25" />
    <IpRange Subnet="40.84.242.0/23" />
    <IpRange Subnet="40.84.244.0/22" />
    <IpRange Subnet="40.86.136.0/21" />
    <IpRange Subnet="40.86.144.0/20" />
    <IpRange Subnet="40.124.0.0/18" />
    <IpRange Subnet="104.215.64.0/18" />
  </Region>
  <Region Name="japanwest">
    <IpRange Subnet="23.98.56.0/26" />
    <IpRange Subnet="23.98.56.64/27" />
    <IpRange Subnet="23.98.56.96/28" />
    <IpRange Subnet="23.98.56.128/26" />
    <IpRange Subnet="23.100.104.0/21" />
    <IpRange Subnet="138.91.16.0/20" />
    <IpRange Subnet="191.233.32.0/19" />
    <IpRange Subnet="191.237.236.0/24" />
    <IpRange Subnet="191.238.80.0/20" />
    <IpRange Subnet="104.46.224.0/20" />
    <IpRange Subnet="40.74.64.0/20" />
    <IpRange Subnet="40.74.80.0/20" />
    <IpRange Subnet="40.74.96.0/19" />
    <IpRange Subnet="40.74.128.0/20" />
    <IpRange Subnet="40.80.64.0/18" />
    <IpRange Subnet="40.80.128.0/20" />
    <IpRange Subnet="104.214.128.0/19" />
    <IpRange Subnet="104.215.0.0/18" />
    <IpRange Subnet="191.238.68.0/26" />
    <IpRange Subnet="191.238.69.0/24" />
    <IpRange Subnet="191.239.96.0/19" />
  </Region>
  <Region Name="japaneast">
    <IpRange Subnet="23.98.57.0/25" />
    <IpRange Subnet="23.98.57.128/27" />
    <IpRange Subnet="23.100.96.0/21" />
    <IpRange Subnet="138.91.0.0/20" />
    <IpRange Subnet="191.234.138.0/24" />
    <IpRange Subnet="104.46.208.0/20" />
    <IpRange Subnet="23.102.64.0/20" />
    <IpRange Subnet="23.102.80.0/24" />
    <IpRange Subnet="40.115.128.0/24" />
    <IpRange Subnet="40.115.129.0/28" />
    <IpRange Subnet="40.115.136.0/21" />
    <IpRange Subnet="40.115.144.0/20" />
    <IpRange Subnet="40.115.160.0/21" />
    <IpRange Subnet="40.115.168.0/24" />
    <IpRange Subnet="40.115.169.0/27" />
    <IpRange Subnet="40.115.169.32/28" />
    <IpRange Subnet="40.115.176.0/20" />
    <IpRange Subnet="40.115.224.0/28" />
    <IpRange Subnet="40.115.224.32/27" />
    <IpRange Subnet="104.41.160.0/19" />
    <IpRange Subnet="191.237.240.0/26" />
    <IpRange Subnet="191.237.240.64/28" />
    <IpRange Subnet="191.237.241.0/24" />
    <IpRange Subnet="13.78.0.0/17" />
    <IpRange Subnet="40.115.129.16/28" />
    <IpRange Subnet="40.115.129.32/27" />
    <IpRange Subnet="40.115.129.64/26" />
    <IpRange Subnet="40.115.129.128/25" />
    <IpRange Subnet="40.115.130.0/23" />
    <IpRange Subnet="40.115.132.0/22" />
    <IpRange Subnet="40.115.169.48/28" />
    <IpRange Subnet="40.115.169.64/26" />
    <IpRange Subnet="40.115.169.128/25" />
    <IpRange Subnet="40.115.170.0/23" />
    <IpRange Subnet="40.115.172.0/22" />
    <IpRange Subnet="40.115.192.0/19" />
    <IpRange Subnet="40.115.224.16/28" />
    <IpRange Subnet="40.115.224.64/26" />
    <IpRange Subnet="40.115.224.128/25" />
    <IpRange Subnet="40.115.225.0/24" />
    <IpRange Subnet="40.115.226.0/23" />
    <IpRange Subnet="40.115.228.0/22" />
    <IpRange Subnet="40.115.232.0/21" />
    <IpRange Subnet="40.115.240.0/20" />
    <IpRange Subnet="13.73.0.0/21" />
    <IpRange Subnet="13.71.128.0/18" />
    <IpRange Subnet="13.73.8.0/21" />
    <IpRange Subnet="13.73.16.0/20" />
  </Region>
  <Region Name="brazilsouth">
    <IpRange Subnet="23.97.96.0/20" />
    <IpRange Subnet="23.97.112.0/25" />
    <IpRange Subnet="23.97.112.128/28" />
    <IpRange Subnet="104.41.0.0/20" />
    <IpRange Subnet="104.41.16.0/26" />
    <IpRange Subnet="104.41.16.64/27" />
    <IpRange Subnet="104.41.17.0/24" />
    <IpRange Subnet="104.41.18.0/23" />
    <IpRange Subnet="104.41.24.0/21" />
    <IpRange Subnet="104.41.32.0/19" />
    <IpRange Subnet="191.232.32.0/21" />
    <IpRange Subnet="191.237.248.0/21" />
    <IpRange Subnet="191.239.240.0/20" />
    <IpRange Subnet="104.41.16.96/27" />
    <IpRange Subnet="104.41.16.128/25" />
    <IpRange Subnet="104.41.20.0/22" />
    <IpRange Subnet="191.232.40.0/21" />
    <IpRange Subnet="191.232.48.0/20" />
  </Region>
  <Region Name="australiaeast">
    <IpRange Subnet="13.70.64.0/18" />
    <IpRange Subnet="13.72.224.0/19" />
    <IpRange Subnet="13.73.192.0/20" />
    <IpRange Subnet="13.75.128.0/17" />
    <IpRange Subnet="23.101.208.0/20" />
    <IpRange Subnet="40.78.192.0/19" />
    <IpRange Subnet="40.126.224.0/19" />
    <IpRange Subnet="104.46.29.0/24" />
    <IpRange Subnet="104.46.30.0/23" />
    <IpRange Subnet="104.46.240.0/20" />
    <IpRange Subnet="104.209.80.0/20" />
    <IpRange Subnet="104.210.64.0/18" />
    <IpRange Subnet="191.238.66.0/25" />
    <IpRange Subnet="191.238.66.128/27" />
    <IpRange Subnet="191.238.66.160/28" />
    <IpRange Subnet="191.238.67.0/24" />
    <IpRange Subnet="191.239.64.0/19" />
  </Region>
  <Region Name="australiasoutheast">
    <IpRange Subnet="13.70.128.0/18" />
    <IpRange Subnet="13.73.96.0/19" />
    <IpRange Subnet="13.77.0.0/18" />
    <IpRange Subnet="23.101.224.0/19" />
    <IpRange Subnet="40.78.224.0/19" />
    <IpRange Subnet="40.115.64.0/19" />
    <IpRange Subnet="40.127.64.0/19" />
    <IpRange Subnet="104.46.28.0/24" />
    <IpRange Subnet="104.209.64.0/20" />
    <IpRange Subnet="191.239.160.0/19" />
    <IpRange Subnet="191.239.192.0/25" />
    <IpRange Subnet="191.239.192.128/27" />
    <IpRange Subnet="191.239.192.160/28" />
    <IpRange Subnet="191.239.192.192/27" />
    <IpRange Subnet="191.239.193.0/24" />
    <IpRange Subnet="191.239.194.0/24" />
    <IpRange Subnet="191.239.195.0/28" />
  </Region>
  <Region Name="indiacentral">
    <IpRange Subnet="104.211.64.0/28" />
    <IpRange Subnet="104.211.65.0/24" />
    <IpRange Subnet="104.211.72.0/21" />
    <IpRange Subnet="104.211.80.0/20" />
    <IpRange Subnet="104.211.96.0/21" />
    <IpRange Subnet="104.211.104.0/26" />
    <IpRange Subnet="104.211.104.64/27" />
    <IpRange Subnet="104.211.104.96/28" />
    <IpRange Subnet="104.211.64.16/28" />
    <IpRange Subnet="104.211.64.32/27" />
    <IpRange Subnet="104.211.64.64/26" />
    <IpRange Subnet="104.211.64.128/25" />
    <IpRange Subnet="104.211.66.0/23" />
    <IpRange Subnet="104.211.68.0/22" />
    <IpRange Subnet="104.211.104.112/28" />
    <IpRange Subnet="104.211.104.128/25" />
    <IpRange Subnet="104.211.105.0/24" />
    <IpRange Subnet="104.211.106.0/23" />
    <IpRange Subnet="104.211.108.0/22" />
    <IpRange Subnet="104.211.112.0/20" />
    <IpRange Subnet="104.47.210.0/23" />
    <IpRange Subnet="13.71.0.0/18" />
  </Region>
  <Region Name="indiawest">
    <IpRange Subnet="104.211.128.0/28" />
    <IpRange Subnet="104.211.129.0/24" />
    <IpRange Subnet="104.211.136.0/21" />
    <IpRange Subnet="104.211.144.0/20" />
    <IpRange Subnet="104.211.160.0/21" />
    <IpRange Subnet="104.211.168.0/27" />
    <IpRange Subnet="104.211.168.32/28" />
    <IpRange Subnet="104.211.168.64/27" />
    <IpRange Subnet="104.211.128.16/28" />
    <IpRange Subnet="104.211.128.32/27" />
    <IpRange Subnet="104.211.128.64/26" />
    <IpRange Subnet="104.211.128.128/25" />
    <IpRange Subnet="104.211.130.0/23" />
    <IpRange Subnet="104.211.132.0/22" />
    <IpRange Subnet="104.211.168.48/28" />
    <IpRange Subnet="104.211.168.96/27" />
    <IpRange Subnet="104.211.168.128/25" />
    <IpRange Subnet="104.211.169.0/24" />
    <IpRange Subnet="104.211.170.0/23" />
    <IpRange Subnet="104.211.172.0/22" />
    <IpRange Subnet="104.211.176.0/20" />
    <IpRange Subnet="104.47.212.0/23" />
  </Region>
  <Region Name="indiasouth">
    <IpRange Subnet="104.211.192.0/28" />
    <IpRange Subnet="104.211.193.0/24" />
    <IpRange Subnet="104.211.200.0/21" />
    <IpRange Subnet="104.211.208.0/20" />
    <IpRange Subnet="104.211.224.0/21" />
    <IpRange Subnet="104.211.232.0/26" />
    <IpRange Subnet="104.211.232.64/27" />
    <IpRange Subnet="104.211.232.96/28" />
    <IpRange Subnet="104.211.232.128/27" />
    <IpRange Subnet="104.211.192.16/28" />
    <IpRange Subnet="104.211.192.32/27" />
    <IpRange Subnet="104.211.192.64/26" />
    <IpRange Subnet="104.211.192.128/25" />
    <IpRange Subnet="104.211.194.0/23" />
    <IpRange Subnet="104.211.196.0/22" />
    <IpRange Subnet="104.211.232.112/28" />
    <IpRange Subnet="104.211.232.160/27" />
    <IpRange Subnet="104.211.232.192/26" />
    <IpRange Subnet="104.211.233.0/24" />
    <IpRange Subnet="104.211.234.0/23" />
    <IpRange Subnet="104.211.236.0/22" />
    <IpRange Subnet="104.211.240.0/20" />
    <IpRange Subnet="104.47.214.0/23" />
    <IpRange Subnet="13.71.64.0/18" />
  </Region>
</AzurePublicIpAddresses>